esayTokenLinux/__init__.py
esayTokenLinux/hello.py
esayTokenLinux-0.1.5.dist-info/METADATA
esayTokenLinux-0.1.5.dist-info/WHEEL
esayTokenLinux-0.1.5.dist-info/top_level.txt
esayTokenLinux-0.1.5.dist-info/RECORD
