Metadata-Version: 2.1
Name: esayTokenLinux
Version: 0.1.5
Summary: esayTokenTest
Home-page: http://example.com
Author: q2536807
Author-email: 616566665@qq.com 
License: UNKNOWN
Platform: any
Requires-Dist: crypto
Requires-Dist: pycrypto
